bmt/__init__.py
bmt/toolkit.py
bmt/utils.py
bmt-1.4.6.dist-info/METADATA
bmt-1.4.6.dist-info/WHEEL
bmt-1.4.6.dist-info/licenses/LICENSE
bmt-1.4.6.dist-info/RECORD
