Metadata-Version: 2.4
Name: bmt
Version: 1.4.6
Summary: Biolink Model Toolkit: A Python API for working with the Biolink Model
License: BSD
License-File: LICENSE
Keywords: schema,linked data,data modeling,biolink,api
Author: Sierra Taylor Moxon
Author-email: sierra.taylor@gmail.com
Requires-Python: >=3.9,<4.0
Classifier: Development Status :: 5 - Production/Stable
Classifier: Environment :: Console
Classifier: Intended Audience :: Developers
Classifier: Intended Audience :: Healthcare Industry
Classifier: Intended Audience :: Science/Research
Classifier: License :: CC0 1.0 Universal (CC0 1.0) Public Domain Dedication
Classifier: License :: Other/Proprietary License
Classifier: Programming Language :: Python :: 3
Classifier: Programming Language :: Python :: 3.9
Classifier: Programming Language :: Python :: 3.10
Classifier: Programming Language :: Python :: 3.11
Classifier: Programming Language :: Python :: 3.12
Classifier: Programming Language :: Python :: 3.13
Classifier: Programming Language :: Python :: 3.14
Classifier: Programming Language :: Python :: 3.8
Classifier: Topic :: Software Development :: Libraries :: Python Modules
Provides-Extra: docs
Requires-Dist: deprecation (>=2.1.0,<3.0.0)
Requires-Dist: linkml-runtime (>=1.6.3,<2.0.0)
Requires-Dist: stringcase (>=1.2.0,<2.0.0)
Project-URL: Documentation, https://biolink.github.io/biolink-model-toolkit/
Project-URL: Repository, https://github.com/biolink/biolink-model-toolkit
